{
  "formatVersion": 1,
  "nodes": [
    {
      "id": "0",
      "name": "Camera",
      "children": [],
      "components": [
        {
          "type": "Camera",
          "config": {
            "formatVersion": 1,
            "mode": "orthographic",
            "fov": 45,
            "orthographicScale": 18,
            "viewport": {
              "x": 0,
              "y": 0,
              "width": 1,
              "height": 1
            },
            "depth": 0,
            "nearClippingPlane": 0.1,
            "farClippingPlane": 1000
          },
          "id": "1"
        },
        {
          "type": "Behavior",
          "config": {
            "behaviorName": "StartGame",
            "propertyValues": {}
          },
          "id": "2"
        }
      ],
      "position": {
        "x": 0,
        "y": 0,
        "z": 5
      },
      "orientation": {
        "x": 0,
        "y": 0,
        "z": 0,
        "w": 1
      },
      "scale": {
        "x": 1,
        "y": 1,
        "z": 1
      },
      "visible": true,
      "layer": 0,
      "prefab": null
    },
    {
      "id": "3",
      "name": "Kos",
      "children": [],
      "components": [
        {
          "type": "SpriteRenderer",
          "config": {
            "formatVersion": 1,
            "spriteAssetId": "35",
            "animationId": null,
            "horizontalFlip": false,
            "verticalFlip": false,
            "castShadow": false,
            "receiveShadow": false,
            "color": "ffffff",
            "overrideOpacity": true,
            "opacity": 0,
            "materialType": "basic",
            "shaderAssetId": null
          },
          "id": "0"
        }
      ],
      "position": {
        "x": -8.82,
        "y": -4.588,
        "z": 2
      },
      "orientation": {
        "x": 0,
        "y": 0,
        "z": 0,
        "w": 1
      },
      "scale": {
        "x": 0.02,
        "y": 0.02,
        "z": 1
      },
      "visible": true,
      "layer": 0,
      "prefab": null
    },
    {
      "id": "7",
      "name": "KosSprite",
      "children": [],
      "components": [
        {
          "type": "SpriteRenderer",
          "config": {
            "formatVersion": 1,
            "spriteAssetId": "3",
            "animationId": "0",
            "horizontalFlip": false,
            "verticalFlip": false,
            "castShadow": false,
            "receiveShadow": false,
            "color": "ffffff",
            "overrideOpacity": false,
            "opacity": null,
            "materialType": "basic",
            "shaderAssetId": null
          },
          "id": "0"
        }
      ],
      "position": {
        "x": 7.489,
        "y": -3.898,
        "z": 2
      },
      "orientation": {
        "x": 0,
        "y": 0,
        "z": 0,
        "w": 1
      },
      "scale": {
        "x": 1,
        "y": 1,
        "z": 1
      },
      "visible": false,
      "layer": 0,
      "prefab": null
    },
    {
      "id": "8",
      "name": "VirusSprite",
      "children": [
        {
          "id": "9",
          "name": "Virus 1",
          "children": [],
          "components": [
            {
              "type": "SpriteRenderer",
              "config": {
                "formatVersion": 1,
                "spriteAssetId": "15",
                "animationId": "0",
                "horizontalFlip": false,
                "verticalFlip": false,
                "castShadow": false,
                "receiveShadow": false,
                "color": "ffffff",
                "overrideOpacity": false,
                "opacity": null,
                "materialType": "basic",
                "shaderAssetId": null
              },
              "id": "0"
            }
          ],
          "position": {
            "x": -2.283475399017334,
            "y": 3.476022720336914,
            "z": 0
          },
          "orientation": {
            "x": 0,
            "y": 0,
            "z": 0,
            "w": 1
          },
          "scale": {
            "x": 1,
            "y": 1,
            "z": 1
          },
          "visible": true,
          "layer": 0,
          "prefab": null
        },
        {
          "id": "10",
          "name": "Virus 2",
          "children": [],
          "components": [
            {
              "type": "SpriteRenderer",
              "config": {
                "formatVersion": 1,
                "spriteAssetId": "15",
                "animationId": "0",
                "horizontalFlip": false,
                "verticalFlip": false,
                "castShadow": false,
                "receiveShadow": false,
                "color": "ffffff",
                "overrideOpacity": false,
                "opacity": null,
                "materialType": "basic",
                "shaderAssetId": null
              },
              "id": "0"
            }
          ],
          "position": {
            "x": 1.6797289848327637,
            "y": 4.0857462882995605,
            "z": 0
          },
          "orientation": {
            "x": 0,
            "y": 0,
            "z": 0,
            "w": 1
          },
          "scale": {
            "x": 0.5,
            "y": 0.5,
            "z": 0.5
          },
          "visible": true,
          "layer": 0,
          "prefab": null
        },
        {
          "id": "11",
          "name": "Virus 3",
          "children": [],
          "components": [
            {
              "type": "SpriteRenderer",
              "config": {
                "formatVersion": 1,
                "spriteAssetId": "15",
                "animationId": "0",
                "horizontalFlip": false,
                "verticalFlip": false,
                "castShadow": false,
                "receiveShadow": false,
                "color": "ffffff",
                "overrideOpacity": false,
                "opacity": null,
                "materialType": "basic",
                "shaderAssetId": null
              },
              "id": "0"
            }
          ],
          "position": {
            "x": 1.303134799003601,
            "y": 3.0635623931884766,
            "z": 0
          },
          "orientation": {
            "x": 0,
            "y": 0,
            "z": 0,
            "w": 1
          },
          "scale": {
            "x": 0.5,
            "y": 0.5,
            "z": 0.5
          },
          "visible": true,
          "layer": 0,
          "prefab": null
        }
      ],
      "components": [],
      "position": {
        "x": 0,
        "y": 0,
        "z": 2
      },
      "orientation": {
        "x": 0,
        "y": 0,
        "z": 0,
        "w": 1
      },
      "scale": {
        "x": 2,
        "y": 2,
        "z": 2
      },
      "visible": false,
      "layer": 0,
      "prefab": null
    },
    {
      "id": "4",
      "name": "Background",
      "children": [
        {
          "id": "5",
          "name": "Main",
          "children": [],
          "components": [
            {
              "type": "SpriteRenderer",
              "config": {
                "formatVersion": 1,
                "spriteAssetId": "57",
                "animationId": null,
                "horizontalFlip": false,
                "verticalFlip": false,
                "castShadow": false,
                "receiveShadow": false,
                "color": "ffffff",
                "overrideOpacity": false,
                "opacity": null,
                "materialType": "basic",
                "shaderAssetId": null
              },
              "id": "0"
            }
          ],
          "position": {
            "x": 0,
            "y": 0,
            "z": 1
          },
          "orientation": {
            "x": 0,
            "y": 0,
            "z": 0,
            "w": 1
          },
          "scale": {
            "x": 1,
            "y": 1,
            "z": 1
          },
          "visible": true,
          "layer": 0,
          "prefab": null
        },
        {
          "id": "6",
          "name": "Instructions",
          "children": [],
          "components": [
            {
              "type": "SpriteRenderer",
              "config": {
                "formatVersion": 1,
                "spriteAssetId": "58",
                "animationId": null,
                "horizontalFlip": false,
                "verticalFlip": false,
                "castShadow": false,
                "receiveShadow": false,
                "color": "ffffff",
                "overrideOpacity": false,
                "opacity": null,
                "materialType": "basic",
                "shaderAssetId": null
              },
              "id": "0"
            }
          ],
          "position": {
            "x": 0,
            "y": 0,
            "z": 0
          },
          "orientation": {
            "x": 0,
            "y": 0,
            "z": 0,
            "w": 1
          },
          "scale": {
            "x": 1,
            "y": 1,
            "z": 1
          },
          "visible": true,
          "layer": 0,
          "prefab": null
        }
      ],
      "components": [],
      "position": {
        "x": -0.29080596566200256,
        "y": 0.788838803768158,
        "z": 0
      },
      "orientation": {
        "x": 0,
        "y": 0,
        "z": 0,
        "w": 1
      },
      "scale": {
        "x": 1,
        "y": 1,
        "z": 1
      },
      "visible": true,
      "layer": 0,
      "prefab": null
    }
  ]
}